tokencrush_langchain/__init__.py
tokencrush_langchain/client.py
tokencrush_langchain/runnable.py
tokencrush_langchain-0.1.0.dist-info/licenses/LICENSE
tokencrush_langchain-0.1.0.dist-info/METADATA
tokencrush_langchain-0.1.0.dist-info/WHEEL
tokencrush_langchain-0.1.0.dist-info/top_level.txt
tokencrush_langchain-0.1.0.dist-info/RECORD
