Metadata-Version: 2.4
Name: tokencrush-langchain
Version: 0.1.0
Summary: LangChain Runnable client for TokenCrush prompt optimization API (/v1/crush)
Author-email: TokenCrush <support@tokencrush.ai>
License: MIT
Project-URL: Homepage, https://tokencrush.ai
Project-URL: Repository, https://github.com/tokencrush/langchain
Project-URL: Issues, https://github.com/tokencrush/langchain/issues
Keywords: langchain,token,prompt,optimization,tokencrush
Classifier: Programming Language :: Python :: 3
Classifier: Programming Language :: Python :: 3 :: Only
Classifier: License :: OSI Approved :: MIT License
Classifier: Operating System :: OS Independent
Requires-Python: >=3.9
License-File: LICENSE
Requires-Dist: httpx>=0.27
Requires-Dist: pydantic>=2.7
Requires-Dist: langchain-core>=0.2.0
Provides-Extra: dev
Requires-Dist: pytest>=8.0; extra == "dev"
Requires-Dist: build>=1.2.1; extra == "dev"
Dynamic: license-file
